m3o_py/__init__.py
m3o_py/address.py
m3o_py/answer.py
m3o_py/cache.py
m3o_py/contacts.py
m3o_py/db.py
m3o_py/id.py
m3o_py/ip.py
m3o_py/joke.py
m3o_py/twitter.py
m3o_py/weather.py
m3o_py-0.1.1a1.dist-info/LICENSE
m3o_py-0.1.1a1.dist-info/WHEEL
m3o_py-0.1.1a1.dist-info/METADATA
m3o_py-0.1.1a1.dist-info/RECORD
