Metadata-Version: 2.1
Name: m3o-py
Version: 0.1.1a1
Summary: Python-library for M3O
Home-page: https://github.com/mawoka-myblock/m3o-py
Author: Mawoka
Author-email: mawoka-myblock@e.email
Requires-Python: >=3.10,<4.0
Classifier: Programming Language :: Python :: 3
Classifier: Programming Language :: Python :: 3.10
Provides-Extra: aiodns
Requires-Dist: aiodns (>=3.0.0,<4.0.0); extra == "aiodns"
Requires-Dist: aiohttp (>=3.8.1,<4.0.0)
Requires-Dist: pydantic (>=1.9.0,<2.0.0)
Project-URL: Repository, https://github.com/mawoka-myblock/m3o-py
